pyMELTScalc/Barom.py
pyMELTScalc/Compositions.py
pyMELTScalc/GenFuncs.py
pyMELTScalc/Holland.py
pyMELTScalc/Liq.py
pyMELTScalc/MELTS.py
pyMELTScalc/Melting.py
pyMELTScalc/Path.py
pyMELTScalc/Path_wrappers.py
pyMELTScalc/PhaseDiagrams.py
pyMELTScalc/Plotting.py
pyMELTScalc/Saturation.py
pyMELTScalc/__init__.py
pyMELTScalc/_version.py
pyMELTScalc-0.1.30.dist-info/METADATA
pyMELTScalc-0.1.30.dist-info/WHEEL
pyMELTScalc-0.1.30.dist-info/top_level.txt
pyMELTScalc-0.1.30.dist-info/RECORD
