Metadata-Version: 2.1
Name: pyMELTScalc
Version: 0.1.30
Summary: pyMELTScalc
Home-page: https://github.com/gleesonm1/pyMELTScalc
Author: Matthew Gleeson
Author-email: gleesonm@berkeley.edu
License: UNKNOWN
Platform: UNKNOWN
Classifier: Programming Language :: Python :: 3
Classifier: Operating System :: OS Independent
Requires-Python: >=3.7
Requires-Dist: pandas
Requires-Dist: numpy
Requires-Dist: matplotlib
Requires-Dist: scikit-learn
Requires-Dist: scipy
Requires-Dist: julia
Requires-Dist: tinynumpy
Requires-Dist: shapely
Requires-Dist: Thermobar
Requires-Dist: pyMelt
Requires-Dist: PetThermoTools
